[
  {
    "color": "Brown",
    "mfg": {
      "title": "Superior Appraisals",
      "value": "8d78dc95-fea6-487d-b004-e485d3d2c594"
    },
    "part": {
      "title": "PTN-00158493",
      "value": "bc7e1958-2c3e-4da7-ae8b-faa414e7d555"
    },
    "price": {
      "amount": "14.17",
      "currency": {
        "title": "USD",
        "value": "dd4a74f1-e6a3-4aa3-a902-1b54048fa760"
      }
    },
    "qty": {
      "amount": 87,
      "uom": {
        "title": "bag",
        "value": "c2cbc91a-f846-4e8d-9d2d-85d286da6000"
      }
    }
  },
  {
    "color": "Orange",
    "mfg": {
      "title": "Belkin",
      "value": "5f05dbf7-a8c7-486b-a7df-c2e7c6fda67e"
    },
    "part": {
      "title": "PTN-00189456",
      "value": "98053510-5c40-4fcd-990a-b5cacfccd099"
    },
    "price": {
      "amount": "18.06",
      "currency": {
        "title": "USD",
        "value": "dd4a74f1-e6a3-4aa3-a902-1b54048fa760"
      }
    },
    "qty": {
      "amount": 183,
      "uom": {
        "title": "each",
        "value": "0b6c96ae-32ac-401a-b455-b6b2a1512ccb"
      }
    }
  },
  {
    "color": "Cyan",
    "mfg": {
      "title": "Forum Communications",
      "value": "64260c24-fb90-42c3-80ce-fbb22fcfcc19"
    },
    "part": {
      "title": "PTN-00069078",
      "value": "d16d8997-8ec2-4080-bd2d-d1d40a095629"
    },
    "price": {
      "amount": "16.15",
      "currency": {
        "title": "USD",
        "value": "dd4a74f1-e6a3-4aa3-a902-1b54048fa760"
      }
    },
    "qty": {
      "amount": 227,
      "uom": {
        "title": "each",
        "value": "0b6c96ae-32ac-401a-b455-b6b2a1512ccb"
      }
    }
  },
  {
    "color": "Cyan",
    "mfg": {
      "title": "Netcore",
      "value": "fd4095ea-8c69-4cf8-8b79-aa1128bfd2bc"
    },
    "part": {
      "title": "PTN-00921750",
      "value": "6528d897-0afd-4057-9988-028e172d7921"
    },
    "price": {
      "amount": "10.48",
      "currency": {
        "title": "USD",
        "value": "dd4a74f1-e6a3-4aa3-a902-1b54048fa760"
      }
    },
    "qty": {
      "amount": 298,
      "uom": {
        "title": "each",
        "value": "0b6c96ae-32ac-401a-b455-b6b2a1512ccb"
      }
    }
  },
  {
    "color": "Brown",
    "mfg": {
      "title": "Fiserv",
      "value": "7d6ebe52-0d42-4df2-8bc7-6adb57d35b59"
    },
    "part": {
      "title": "PTN-00521128",
      "value": "eb4e35b1-5738-421e-b1c4-2c881a4f44f9"
    },
    "price": {
      "amount": "10.66",
      "currency": {
        "title": "USD",
        "value": "dd4a74f1-e6a3-4aa3-a902-1b54048fa760"
      }
    },
    "qty": {
      "amount": 262,
      "uom": {
        "title": "each",
        "value": "0b6c96ae-32ac-401a-b455-b6b2a1512ccb"
      }
    }
  },
  {
    "color": "Magenta",
    "mfg": {
      "title": "Archer Daniels Midland",
      "value": "f6377573-b057-4b82-b62c-2283b71f4bdf"
    },
    "part": {
      "title": "PTN-00889958",
      "value": "a3be9f91-6f71-4ac7-8639-304fbe077af3"
    },
    "price": {
      "amount": "16.67",
      "currency": {
        "title": "USD",
        "value": "dd4a74f1-e6a3-4aa3-a902-1b54048fa760"
      }
    },
    "qty": {
      "amount": 268,
      "uom": {
        "title": "each",
        "value": "0b6c96ae-32ac-401a-b455-b6b2a1512ccb"
      }
    }
  },
  {
    "color": "Purple",
    "mfg": {
      "title": "Publix",
      "value": "98b0660d-57f5-406f-b3cf-643ab67ec058"
    },
    "part": {
      "title": "PTN-00943089",
      "value": "9b379801-24e6-4866-ba9e-86d19b3a377b"
    },
    "price": {
      "amount": "15.00",
      "currency": {
        "title": "USD",
        "value": "dd4a74f1-e6a3-4aa3-a902-1b54048fa760"
      }
    },
    "qty": {
      "amount": 285,
      "uom": {
        "title": "bag",
        "value": "c2cbc91a-f846-4e8d-9d2d-85d286da6000"
      }
    }
  },
  {
    "color": "Cyan",
    "mfg": {
      "title": "Autoliv",
      "value": "90fac03a-bc7f-4bdb-a583-e49273a4f300"
    },
    "part": {
      "title": "PTN-00015732",
      "value": "f1dfb865-84c9-4fa1-b839-986e9ac58cf1"
    },
    "price": {
      "amount": "12.24",
      "currency": {
        "title": "USD",
        "value": "dd4a74f1-e6a3-4aa3-a902-1b54048fa760"
      }
    },
    "qty": {
      "amount": 217,
      "uom": {
        "title": "box",
        "value": "48f8c503-9f05-45a6-a168-c641d6dab4e4"
      }
    }
  },
  {
    "color": "Purple",
    "mfg": {
      "title": "Automatic Data Processing",
      "value": "42612907-0924-4299-8dd4-e023a57a77b1"
    },
    "part": {
      "title": "PTN-00493555",
      "value": "2a2f2df5-892c-4d4c-908a-896bc432964c"
    },
    "price": {
      "amount": "19.26",
      "currency": {
        "title": "USD",
        "value": "dd4a74f1-e6a3-4aa3-a902-1b54048fa760"
      }
    },
    "qty": {
      "amount": 218,
      "uom": {
        "title": "each",
        "value": "0b6c96ae-32ac-401a-b455-b6b2a1512ccb"
      }
    }
  },
  {
    "color": "Brown",
    "mfg": {
      "title": "Farnod",
      "value": "0e563fe5-e26b-44ef-8e89-67ce1b0a171f"
    },
    "part": {
      "title": "PTN-00235788",
      "value": "5524202f-b6b1-418f-bbdc-dd803cfd111c"
    },
    "price": {
      "amount": "10.35",
      "currency": {
        "title": "USD",
        "value": "dd4a74f1-e6a3-4aa3-a902-1b54048fa760"
      }
    },
    "qty": {
      "amount": 193,
      "uom": {
        "title": "box",
        "value": "48f8c503-9f05-45a6-a168-c641d6dab4e4"
      }
    }
  },
  {
    "color": "Red",
    "mfg": {
      "title": "Lockheed Martin",
      "value": "aff89168-66b8-4d18-93ba-2ff86023f2d2"
    },
    "part": {
      "title": "PTN-00942544",
      "value": "32d7dcd6-4bf4-4c99-95c5-2015b65fdcf2"
    },
    "price": {
      "amount": "19.61",
      "currency": {
        "title": "USD",
        "value": "dd4a74f1-e6a3-4aa3-a902-1b54048fa760"
      }
    },
    "qty": {
      "amount": 163,
      "uom": {
        "title": "each",
        "value": "0b6c96ae-32ac-401a-b455-b6b2a1512ccb"
      }
    }
  },
  {
    "color": "Brown",
    "mfg": {
      "title": "Nutri G",
      "value": "bb891f62-4c40-4831-b46b-0df002a66c49"
    },
    "part": {
      "title": "PTN-00764521",
      "value": "cf8d92fd-cdc6-4210-82b2-de72e49b6a34"
    },
    "price": {
      "amount": "19.09",
      "currency": {
        "title": "USD",
        "value": "dd4a74f1-e6a3-4aa3-a902-1b54048fa760"
      }
    },
    "qty": {
      "amount": 206,
      "uom": {
        "title": "box",
        "value": "48f8c503-9f05-45a6-a168-c641d6dab4e4"
      }
    }
  },
  {
    "color": "Purple",
    "mfg": {
      "title": "VonMaur",
      "value": "255816ca-42ac-4fe6-8f7c-dd032948dd64"
    },
    "part": {
      "title": "PTN-00455849",
      "value": "67d4a25f-ca00-41d4-b244-88d792a26c74"
    },
    "price": {
      "amount": "12.53",
      "currency": {
        "title": "USD",
        "value": "dd4a74f1-e6a3-4aa3-a902-1b54048fa760"
      }
    },
    "qty": {
      "amount": 296,
      "uom": {
        "title": "each",
        "value": "0b6c96ae-32ac-401a-b455-b6b2a1512ccb"
      }
    }
  },
  {
    "color": "Cyan",
    "mfg": {
      "title": "Omni Tech",
      "value": "0fb79669-655f-4d46-9689-b3152e4c6302"
    },
    "part": {
      "title": "PTN-00898611",
      "value": "542be3b7-5744-440e-b4b1-368db3274162"
    },
    "price": {
      "amount": "15.08",
      "currency": {
        "title": "USD",
        "value": "dd4a74f1-e6a3-4aa3-a902-1b54048fa760"
      }
    },
    "qty": {
      "amount": 205,
      "uom": {
        "title": "pack",
        "value": "95d2e659-e9f1-4cce-b3d2-70a8dcf039ee"
      }
    }
  },
  {
    "color": "Pink",
    "mfg": {
      "title": "Strategy Consulting",
      "value": "8d30f1f1-d177-4bd9-927d-72c8b878df55"
    },
    "part": {
      "title": "PTN-00884596",
      "value": "dab74838-e841-4340-8c36-86d9279a7bca"
    },
    "price": {
      "amount": "13.04",
      "currency": {
        "title": "USD",
        "value": "dd4a74f1-e6a3-4aa3-a902-1b54048fa760"
      }
    },
    "qty": {
      "amount": 147,
      "uom": {
        "title": "bag",
        "value": "c2cbc91a-f846-4e8d-9d2d-85d286da6000"
      }
    }
  },
  {
    "color": "Blue",
    "mfg": {
      "title": "International Business Machines (IBM)",
      "value": "80ae17d5-64e6-40f9-9cb1-01ec493059d1"
    },
    "part": {
      "title": "PTN-00657229",
      "value": "5af90013-0587-4589-a8fc-ed05a64eac45"
    },
    "price": {
      "amount": "17.72",
      "currency": {
        "title": "USD",
        "value": "dd4a74f1-e6a3-4aa3-a902-1b54048fa760"
      }
    },
    "qty": {
      "amount": 267,
      "uom": {
        "title": "bag",
        "value": "c2cbc91a-f846-4e8d-9d2d-85d286da6000"
      }
    }
  },
  {
    "color": "Brown",
    "mfg": {
      "title": "Oreck Corporation",
      "value": "fa994ff6-51dc-466c-81af-520c1ef2bae2"
    },
    "part": {
      "title": "PTN-00223587",
      "value": "a6f0a6f3-85e1-4089-ab0c-9e1a74e8b52d"
    },
    "price": {
      "amount": "10.13",
      "currency": {
        "title": "USD",
        "value": "dd4a74f1-e6a3-4aa3-a902-1b54048fa760"
      }
    },
    "qty": {
      "amount": 154,
      "uom": {
        "title": "each",
        "value": "0b6c96ae-32ac-401a-b455-b6b2a1512ccb"
      }
    }
  },
  {
    "color": "Magenta",
    "mfg": {
      "title": "Zoo York",
      "value": "8e98b579-ca68-46c1-acf0-11d12544a4bf"
    },
    "part": {
      "title": "PTN-00604628",
      "value": "f73489fd-f2a2-4b06-9b0e-673310174713"
    },
    "price": {
      "amount": "15.87",
      "currency": {
        "title": "USD",
        "value": "dd4a74f1-e6a3-4aa3-a902-1b54048fa760"
      }
    },
    "qty": {
      "amount": 240,
      "uom": {
        "title": "box",
        "value": "48f8c503-9f05-45a6-a168-c641d6dab4e4"
      }
    }
  },
  {
    "color": "Red",
    "mfg": {
      "title": "Spanx",
      "value": "b3f30a86-d8a7-44b3-beb3-e012a53afe4d"
    },
    "part": {
      "title": "PTN-00322112",
      "value": "9b60679b-622d-4e13-8738-c5040379b4f0"
    },
    "price": {
      "amount": "15.47",
      "currency": {
        "title": "USD",
        "value": "dd4a74f1-e6a3-4aa3-a902-1b54048fa760"
      }
    },
    "qty": {
      "amount": 226,
      "uom": {
        "title": "bag",
        "value": "c2cbc91a-f846-4e8d-9d2d-85d286da6000"
      }
    }
  },
  {
    "color": "Brown",
    "mfg": {
      "title": "Pro Property Maintenance",
      "value": "a855dd83-4d2f-4134-9085-6084811f8ce5"
    },
    "part": {
      "title": "PTN-00331120",
      "value": "21f76111-ae15-4925-8021-43b7d5c1a3da"
    },
    "price": {
      "amount": "19.98",
      "currency": {
        "title": "USD",
        "value": "dd4a74f1-e6a3-4aa3-a902-1b54048fa760"
      }
    },
    "qty": {
      "amount": 150,
      "uom": {
        "title": "bag",
        "value": "c2cbc91a-f846-4e8d-9d2d-85d286da6000"
      }
    }
  },
  {
    "color": "Purple",
    "mfg": {
      "title": "Service Corporation International (SCI)",
      "value": "253ab477-f52f-4314-bde5-cf550ab04600"
    },
    "part": {
      "title": "PTN-00327616",
      "value": "55961986-0e87-4ffe-90a9-a7b756bca4f0"
    },
    "price": {
      "amount": "13.67",
      "currency": {
        "title": "USD",
        "value": "dd4a74f1-e6a3-4aa3-a902-1b54048fa760"
      }
    },
    "qty": {
      "amount": 124,
      "uom": {
        "title": "bag",
        "value": "c2cbc91a-f846-4e8d-9d2d-85d286da6000"
      }
    }
  },
  {
    "color": "Brown",
    "mfg": {
      "title": "ZOMM, LLC",
      "value": "8b137073-8715-4426-b651-21168149b0a4"
    },
    "part": {
      "title": "PTN-00187431",
      "value": "210acc46-0961-4110-9ac7-b9cc2548eff9"
    },
    "price": {
      "amount": "18.30",
      "currency": {
        "title": "USD",
        "value": "dd4a74f1-e6a3-4aa3-a902-1b54048fa760"
      }
    },
    "qty": {
      "amount": 192,
      "uom": {
        "title": "bag",
        "value": "c2cbc91a-f846-4e8d-9d2d-85d286da6000"
      }
    }
  },
  {
    "color": "Purple",
    "mfg": {
      "title": "Exact Solutions",
      "value": "9bb7688b-a0d6-4807-a480-44945688d14c"
    },
    "part": {
      "title": "PTN-00927056",
      "value": "38a01742-440f-49f6-a58d-86cad4f4b727"
    },
    "price": {
      "amount": "12.60",
      "currency": {
        "title": "USD",
        "value": "dd4a74f1-e6a3-4aa3-a902-1b54048fa760"
      }
    },
    "qty": {
      "amount": 221,
      "uom": {
        "title": "bag",
        "value": "c2cbc91a-f846-4e8d-9d2d-85d286da6000"
      }
    }
  },
  {
    "color": "Black",
    "mfg": {
      "title": "Adaptaz",
      "value": "227bfae1-3f02-49fb-b258-786d8754a551"
    },
    "part": {
      "title": "PTN-00876308",
      "value": "073ea377-347b-4088-8373-f97d05d3c734"
    },
    "price": {
      "amount": "11.74",
      "currency": {
        "title": "USD",
        "value": "dd4a74f1-e6a3-4aa3-a902-1b54048fa760"
      }
    },
    "qty": {
      "amount": 176,
      "uom": {
        "title": "box",
        "value": "48f8c503-9f05-45a6-a168-c641d6dab4e4"
      }
    }
  },
  {
    "color": "Orange",
    "mfg": {
      "title": "Nortax",
      "value": "598b339c-6314-4055-8760-8f8a39fbb53a"
    },
    "part": {
      "title": "PTN-00002941",
      "value": "2559a5e7-e311-4a33-8f95-8688f2ae3f54"
    },
    "price": {
      "amount": "11.11",
      "currency": {
        "title": "USD",
        "value": "dd4a74f1-e6a3-4aa3-a902-1b54048fa760"
      }
    },
    "qty": {
      "amount": 281,
      "uom": {
        "title": "pack",
        "value": "95d2e659-e9f1-4cce-b3d2-70a8dcf039ee"
      }
    }
  },
  {
    "color": "Pink",
    "mfg": {
      "title": "Principal Financial Group",
      "value": "a106fb9d-73ac-4af9-a862-ca095bc74280"
    },
    "part": {
      "title": "PTN-00103252",
      "value": "6933192c-b512-4d05-b15c-77678422e97d"
    },
    "price": {
      "amount": "13.40",
      "currency": {
        "title": "USD",
        "value": "dd4a74f1-e6a3-4aa3-a902-1b54048fa760"
      }
    },
    "qty": {
      "amount": 139,
      "uom": {
        "title": "pack",
        "value": "95d2e659-e9f1-4cce-b3d2-70a8dcf039ee"
      }
    }
  },
  {
    "color": "Cyan",
    "mfg": {
      "title": "Dover Corporation",
      "value": "35dbfa7f-f778-45f1-8f69-a892a5448ec5"
    },
    "part": {
      "title": "PTN-00797859",
      "value": "b7e0c34e-897b-41e8-a20b-902f72530a7a"
    },
    "price": {
      "amount": "14.75",
      "currency": {
        "title": "USD",
        "value": "dd4a74f1-e6a3-4aa3-a902-1b54048fa760"
      }
    },
    "qty": {
      "amount": 219,
      "uom": {
        "title": "each",
        "value": "0b6c96ae-32ac-401a-b455-b6b2a1512ccb"
      }
    }
  },
  {
    "color": "Red",
    "mfg": {
      "title": "Spectrum Brands",
      "value": "f9b2bb80-fbe4-40bf-ae55-b17cef6305a1"
    },
    "part": {
      "title": "PTN-00404424",
      "value": "77aa7676-9d5a-493f-86f3-c9b1dadb47aa"
    },
    "price": {
      "amount": "10.37",
      "currency": {
        "title": "USD",
        "value": "dd4a74f1-e6a3-4aa3-a902-1b54048fa760"
      }
    },
    "qty": {
      "amount": 231,
      "uom": {
        "title": "each",
        "value": "0b6c96ae-32ac-401a-b455-b6b2a1512ccb"
      }
    }
  },
  {
    "color": "White",
    "mfg": {
      "title": "Textron Inc.",
      "value": "f67d9c92-9ce3-4256-bb57-88e08d1c4b30"
    },
    "part": {
      "title": "PTN-00135540",
      "value": "2a0d0fd0-c4f3-4623-a457-f0a3a952e8f9"
    },
    "price": {
      "amount": "19.50",
      "currency": {
        "title": "USD",
        "value": "dd4a74f1-e6a3-4aa3-a902-1b54048fa760"
      }
    },
    "qty": {
      "amount": 153,
      "uom": {
        "title": "bag",
        "value": "c2cbc91a-f846-4e8d-9d2d-85d286da6000"
      }
    }
  },
  {
    "color": "Cyan",
    "mfg": {
      "title": "Adobe Systems Inc.",
      "value": "f8fef1c5-e09d-45ee-8eb7-44bb3f0b1c81"
    },
    "part": {
      "title": "PTN-00337775",
      "value": "1fa98fb1-e972-4c8b-8906-c9b0549bf890"
    },
    "price": {
      "amount": "13.79",
      "currency": {
        "title": "USD",
        "value": "dd4a74f1-e6a3-4aa3-a902-1b54048fa760"
      }
    },
    "qty": {
      "amount": 261,
      "uom": {
        "title": "pack",
        "value": "95d2e659-e9f1-4cce-b3d2-70a8dcf039ee"
      }
    }
  },
  {
    "color": "Brown",
    "mfg": {
      "title": "Future Plan",
      "value": "05c91eba-777f-41f9-9a8b-a1d908aae208"
    },
    "part": {
      "title": "PTN-00644342",
      "value": "515835e8-7e79-4c3b-9480-cad9f3cb76b6"
    },
    "price": {
      "amount": "16.10",
      "currency": {
        "title": "USD",
        "value": "dd4a74f1-e6a3-4aa3-a902-1b54048fa760"
      }
    },
    "qty": {
      "amount": 212,
      "uom": {
        "title": "box",
        "value": "48f8c503-9f05-45a6-a168-c641d6dab4e4"
      }
    }
  },
  {
    "color": "Beige",
    "mfg": {
      "title": "West Liberty Foods",
      "value": "e336b6dc-269f-48b0-9717-8d2ec35a6867"
    },
    "part": {
      "title": "PTN-00982032",
      "value": "dabf07f1-7971-4d3a-a248-b095f81e0ab4"
    },
    "price": {
      "amount": "10.24",
      "currency": {
        "title": "USD",
        "value": "dd4a74f1-e6a3-4aa3-a902-1b54048fa760"
      }
    },
    "qty": {
      "amount": 266,
      "uom": {
        "title": "each",
        "value": "0b6c96ae-32ac-401a-b455-b6b2a1512ccb"
      }
    }
  },
  {
    "color": "Cyan",
    "mfg": {
      "title": "Maxiserve",
      "value": "092fcede-4a4f-4da9-97fc-42243a142953"
    },
    "part": {
      "title": "PTN-00580546",
      "value": "40e82373-edb0-4133-b68a-672d222a39ae"
    },
    "price": {
      "amount": "14.05",
      "currency": {
        "title": "USD",
        "value": "dd4a74f1-e6a3-4aa3-a902-1b54048fa760"
      }
    },
    "qty": {
      "amount": 197,
      "uom": {
        "title": "pack",
        "value": "95d2e659-e9f1-4cce-b3d2-70a8dcf039ee"
      }
    }
  },
  {
    "color": "White",
    "mfg": {
      "title": "Shirokiya",
      "value": "7505bb95-8694-47d9-ac09-2a018b2ac34b"
    },
    "part": {
      "title": "PTN-00877666",
      "value": "a2dc45da-4f3d-4604-9913-3b1a5745d6cd"
    },
    "price": {
      "amount": "14.83",
      "currency": {
        "title": "USD",
        "value": "dd4a74f1-e6a3-4aa3-a902-1b54048fa760"
      }
    },
    "qty": {
      "amount": 208,
      "uom": {
        "title": "box",
        "value": "48f8c503-9f05-45a6-a168-c641d6dab4e4"
      }
    }
  },
  {
    "color": "Purple",
    "mfg": {
      "title": "Monmax",
      "value": "6330032f-d1ba-4bc9-8a4b-215e8d2ad6eb"
    },
    "part": {
      "title": "PTN-00127829",
      "value": "53cc8eee-f8a7-468b-b653-011f7574455b"
    },
    "price": {
      "amount": "10.64",
      "currency": {
        "title": "USD",
        "value": "dd4a74f1-e6a3-4aa3-a902-1b54048fa760"
      }
    },
    "qty": {
      "amount": 216,
      "uom": {
        "title": "bag",
        "value": "c2cbc91a-f846-4e8d-9d2d-85d286da6000"
      }
    }
  },
  {
    "color": "Orange",
    "mfg": {
      "title": "Arkeia Software",
      "value": "d1d4ea73-4014-4723-8dab-243948dd6e01"
    },
    "part": {
      "title": "PTN-00154085",
      "value": "9e7cfef8-1e9f-4d8b-8193-9829867328d5"
    },
    "price": {
      "amount": "16.04",
      "currency": {
        "title": "USD",
        "value": "dd4a74f1-e6a3-4aa3-a902-1b54048fa760"
      }
    },
    "qty": {
      "amount": 199,
      "uom": {
        "title": "each",
        "value": "0b6c96ae-32ac-401a-b455-b6b2a1512ccb"
      }
    }
  },
  {
    "color": "Blue",
    "mfg": {
      "title": "Perisolution",
      "value": "8047a77c-f55f-4911-afbf-da8c8d8cf144"
    },
    "part": {
      "title": "PTN-00181139",
      "value": "61ae8a13-c280-4132-b464-8336d51a5e3a"
    },
    "price": {
      "amount": "11.73",
      "currency": {
        "title": "USD",
        "value": "dd4a74f1-e6a3-4aa3-a902-1b54048fa760"
      }
    },
    "qty": {
      "amount": 177,
      "uom": {
        "title": "each",
        "value": "0b6c96ae-32ac-401a-b455-b6b2a1512ccb"
      }
    }
  },
  {
    "color": "Green",
    "mfg": {
      "title": "Home Depot",
      "value": "753f79ec-1cb0-4d39-b9c3-c74f72bd6120"
    },
    "part": {
      "title": "PTN-00385409",
      "value": "e698cd73-18a5-4ef2-9ef5-f2c7c09f253a"
    },
    "price": {
      "amount": "19.96",
      "currency": {
        "title": "USD",
        "value": "dd4a74f1-e6a3-4aa3-a902-1b54048fa760"
      }
    },
    "qty": {
      "amount": 298,
      "uom": {
        "title": "box",
        "value": "48f8c503-9f05-45a6-a168-c641d6dab4e4"
      }
    }
  },
  {
    "color": "Beige",
    "mfg": {
      "title": "Wealthy Ideas",
      "value": "f8cd9247-f94e-418e-8b77-1c097f955ddb"
    },
    "part": {
      "title": "PTN-00546398",
      "value": "30fba3ce-12d2-4ae8-9421-f79ca0050ce1"
    },
    "price": {
      "amount": "10.13",
      "currency": {
        "title": "USD",
        "value": "dd4a74f1-e6a3-4aa3-a902-1b54048fa760"
      }
    },
    "qty": {
      "amount": 120,
      "uom": {
        "title": "pack",
        "value": "95d2e659-e9f1-4cce-b3d2-70a8dcf039ee"
      }
    }
  },
  {
    "color": "Green",
    "mfg": {
      "title": "AnaSpec",
      "value": "e06f212d-2439-4600-8fb7-3cfb997423ad"
    },
    "part": {
      "title": "PTN-00920840",
      "value": "9d9309f8-b58a-4011-a5eb-24b3600fc987"
    },
    "price": {
      "amount": "12.80",
      "currency": {
        "title": "USD",
        "value": "dd4a74f1-e6a3-4aa3-a902-1b54048fa760"
      }
    },
    "qty": {
      "amount": 122,
      "uom": {
        "title": "box",
        "value": "48f8c503-9f05-45a6-a168-c641d6dab4e4"
      }
    }
  },
  {
    "color": "Cyan",
    "mfg": {
      "title": "Calpine",
      "value": "36e2f7c6-a7b6-4951-9ebd-7c655d59730c"
    },
    "part": {
      "title": "PTN-00719884",
      "value": "79b49c30-a9d7-485a-bc83-e0822e503dd3"
    },
    "price": {
      "amount": "18.01",
      "currency": {
        "title": "USD",
        "value": "dd4a74f1-e6a3-4aa3-a902-1b54048fa760"
      }
    },
    "qty": {
      "amount": 149,
      "uom": {
        "title": "pack",
        "value": "95d2e659-e9f1-4cce-b3d2-70a8dcf039ee"
      }
    }
  },
  {
    "color": "Purple",
    "mfg": {
      "title": "Electronic Geek",
      "value": "1c111b6f-d78d-4ea0-9ebc-fd8e6ea10386"
    },
    "part": {
      "title": "PTN-00818628",
      "value": "aff7c804-9524-4706-851b-ee491fd21d1e"
    },
    "price": {
      "amount": "13.65",
      "currency": {
        "title": "USD",
        "value": "dd4a74f1-e6a3-4aa3-a902-1b54048fa760"
      }
    },
    "qty": {
      "amount": 278,
      "uom": {
        "title": "pack",
        "value": "95d2e659-e9f1-4cce-b3d2-70a8dcf039ee"
      }
    }
  },
  {
    "color": "Green",
    "mfg": {
      "title": "Corning Incorporated",
      "value": "d9c2eb96-3ee1-431d-879e-43fe4acfa59d"
    },
    "part": {
      "title": "PTN-00192870",
      "value": "2bc548df-d1b0-4d70-81c2-caa9245c8df1"
    },
    "price": {
      "amount": "18.96",
      "currency": {
        "title": "USD",
        "value": "dd4a74f1-e6a3-4aa3-a902-1b54048fa760"
      }
    },
    "qty": {
      "amount": 207,
      "uom": {
        "title": "box",
        "value": "48f8c503-9f05-45a6-a168-c641d6dab4e4"
      }
    }
  },
  {
    "color": "Pink",
    "mfg": {
      "title": "Adapt",
      "value": "91165724-9354-4308-a472-c861d0e81bc2"
    },
    "part": {
      "title": "PTN-00599108",
      "value": "0c1bc09c-f78d-4be4-8b49-07c6f7d4acd8"
    },
    "price": {
      "amount": "16.47",
      "currency": {
        "title": "USD",
        "value": "dd4a74f1-e6a3-4aa3-a902-1b54048fa760"
      }
    },
    "qty": {
      "amount": 222,
      "uom": {
        "title": "each",
        "value": "0b6c96ae-32ac-401a-b455-b6b2a1512ccb"
      }
    }
  },
  {
    "color": "Black",
    "mfg": {
      "title": "One-Up Realtors",
      "value": "58509c08-6efa-42cf-8b47-d51a1a7d6a93"
    },
    "part": {
      "title": "PTN-00111603",
      "value": "25b135ce-4975-4d97-b9a3-c9506bd31074"
    },
    "price": {
      "amount": "19.12",
      "currency": {
        "title": "USD",
        "value": "dd4a74f1-e6a3-4aa3-a902-1b54048fa760"
      }
    },
    "qty": {
      "amount": 239,
      "uom": {
        "title": "each",
        "value": "0b6c96ae-32ac-401a-b455-b6b2a1512ccb"
      }
    }
  },
  {
    "color": "Purple",
    "mfg": {
      "title": "Verbatim Corporation",
      "value": "3023fd73-c3f9-40b8-9ea0-b06bb89ba1e6"
    },
    "part": {
      "title": "PTN-00275269",
      "value": "eadda4bc-ffad-451a-9e31-27dc660a1559"
    },
    "price": {
      "amount": "19.20",
      "currency": {
        "title": "USD",
        "value": "dd4a74f1-e6a3-4aa3-a902-1b54048fa760"
      }
    },
    "qty": {
      "amount": 239,
      "uom": {
        "title": "each",
        "value": "0b6c96ae-32ac-401a-b455-b6b2a1512ccb"
      }
    }
  },
  {
    "color": "Beige",
    "mfg": {
      "title": "Maxtor Corporation",
      "value": "ae947482-eae0-41c8-a467-3204ceb29c80"
    },
    "part": {
      "title": "PTN-00951767",
      "value": "e03e030a-feca-48ab-83d1-e1a6ffa2393e"
    },
    "price": {
      "amount": "15.53",
      "currency": {
        "title": "USD",
        "value": "dd4a74f1-e6a3-4aa3-a902-1b54048fa760"
      }
    },
    "qty": {
      "amount": 147,
      "uom": {
        "title": "bag",
        "value": "c2cbc91a-f846-4e8d-9d2d-85d286da6000"
      }
    }
  },
  {
    "color": "Red",
    "mfg": {
      "title": "Biggby Coffee",
      "value": "e719fa9d-41c5-4f76-ae00-b094aee8e8e0"
    },
    "part": {
      "title": "PTN-00370730",
      "value": "76c9cec3-bb60-47fa-b441-634a9f0a6675"
    },
    "price": {
      "amount": "16.12",
      "currency": {
        "title": "USD",
        "value": "dd4a74f1-e6a3-4aa3-a902-1b54048fa760"
      }
    },
    "qty": {
      "amount": 119,
      "uom": {
        "title": "pack",
        "value": "95d2e659-e9f1-4cce-b3d2-70a8dcf039ee"
      }
    }
  },
  {
    "color": "Orange",
    "mfg": {
      "title": "Carnival Cruise Lines",
      "value": "25ddaacb-6d5c-452a-bf88-54d54155800c"
    },
    "part": {
      "title": "PTN-00050634",
      "value": "eaab1d3e-eb6d-4084-9e30-29c6928a8a0d"
    },
    "price": {
      "amount": "18.89",
      "currency": {
        "title": "USD",
        "value": "dd4a74f1-e6a3-4aa3-a902-1b54048fa760"
      }
    },
    "qty": {
      "amount": 128,
      "uom": {
        "title": "each",
        "value": "0b6c96ae-32ac-401a-b455-b6b2a1512ccb"
      }
    }
  },
  {
    "color": "Red",
    "mfg": {
      "title": "Strength Gurus",
      "value": "b768f887-5798-48a9-a6e2-123b88bf26e2"
    },
    "part": {
      "title": "PTN-00984246",
      "value": "89b595d6-4f2e-4bc1-8f56-6679cc2e4aae"
    },
    "price": {
      "amount": "10.80",
      "currency": {
        "title": "USD",
        "value": "dd4a74f1-e6a3-4aa3-a902-1b54048fa760"
      }
    },
    "qty": {
      "amount": 294,
      "uom": {
        "title": "bag",
        "value": "c2cbc91a-f846-4e8d-9d2d-85d286da6000"
      }
    }
  },
  {
    "color": "Green",
    "mfg": {
      "title": "Nordstrom",
      "value": "2ece5a18-3bda-42db-adf5-f0ea21d16247"
    },
    "part": {
      "title": "PTN-00708250",
      "value": "d820d390-6569-4c33-97b2-3b85a2d93032"
    },
    "price": {
      "amount": "10.76",
      "currency": {
        "title": "USD",
        "value": "dd4a74f1-e6a3-4aa3-a902-1b54048fa760"
      }
    },
    "qty": {
      "amount": 273,
      "uom": {
        "title": "pack",
        "value": "95d2e659-e9f1-4cce-b3d2-70a8dcf039ee"
      }
    }
  },
  {
    "color": "Beige",
    "mfg": {
      "title": "Interstate Batteries",
      "value": "c24bb9c9-e964-49ec-9184-4baf380d0845"
    },
    "part": {
      "title": "PTN-00910776",
      "value": "e19b4dab-dad3-4ae6-956b-cdc0289a9878"
    },
    "price": {
      "amount": "13.71",
      "currency": {
        "title": "USD",
        "value": "dd4a74f1-e6a3-4aa3-a902-1b54048fa760"
      }
    },
    "qty": {
      "amount": 105,
      "uom": {
        "title": "bag",
        "value": "c2cbc91a-f846-4e8d-9d2d-85d286da6000"
      }
    }
  },
  {
    "color": "Orange",
    "mfg": {
      "title": "First Choice Yard Help",
      "value": "884a6104-01f9-4be2-ab6e-134a499575be"
    },
    "part": {
      "title": "PTN-00506303",
      "value": "52d5092e-5e73-40ee-a2cf-162df8471de3"
    },
    "price": {
      "amount": "14.90",
      "currency": {
        "title": "USD",
        "value": "dd4a74f1-e6a3-4aa3-a902-1b54048fa760"
      }
    },
    "qty": {
      "amount": 104,
      "uom": {
        "title": "each",
        "value": "0b6c96ae-32ac-401a-b455-b6b2a1512ccb"
      }
    }
  },
  {
    "color": "Purple",
    "mfg": {
      "title": "Wise Appraisals",
      "value": "f3817e3b-e275-46c9-9117-705f0b99e7b7"
    },
    "part": {
      "title": "PTN-00905920",
      "value": "48e827de-39a2-426b-97f8-d18204e6d6af"
    },
    "price": {
      "amount": "18.84",
      "currency": {
        "title": "USD",
        "value": "dd4a74f1-e6a3-4aa3-a902-1b54048fa760"
      }
    },
    "qty": {
      "amount": 85,
      "uom": {
        "title": "box",
        "value": "48f8c503-9f05-45a6-a168-c641d6dab4e4"
      }
    }
  },
  {
    "color": "Beige",
    "mfg": {
      "title": "International Business Machines (IBM)",
      "value": "c3632797-159e-4810-b8fc-24004a6b7d24"
    },
    "part": {
      "title": "PTN-00238345",
      "value": "5e3a88dc-29f6-4cf8-9c83-49e43f99f6fd"
    },
    "price": {
      "amount": "14.49",
      "currency": {
        "title": "USD",
        "value": "dd4a74f1-e6a3-4aa3-a902-1b54048fa760"
      }
    },
    "qty": {
      "amount": 113,
      "uom": {
        "title": "pack",
        "value": "95d2e659-e9f1-4cce-b3d2-70a8dcf039ee"
      }
    }
  },
  {
    "color": "Brown",
    "mfg": {
      "title": "Crowley Maritime Corporation",
      "value": "89325c46-8785-4069-a96c-0a54a4c0ee62"
    },
    "part": {
      "title": "PTN-00301477",
      "value": "06fcacef-fff0-44c8-8c64-0d3732de927f"
    },
    "price": {
      "amount": "19.91",
      "currency": {
        "title": "USD",
        "value": "dd4a74f1-e6a3-4aa3-a902-1b54048fa760"
      }
    },
    "qty": {
      "amount": 272,
      "uom": {
        "title": "box",
        "value": "48f8c503-9f05-45a6-a168-c641d6dab4e4"
      }
    }
  },
  {
    "color": "Red",
    "mfg": {
      "title": "Infor",
      "value": "6c36e7ff-4a98-4b24-b2d0-860d16102a28"
    },
    "part": {
      "title": "PTN-00777010",
      "value": "381c4974-46c0-45a7-81b3-7693f2ec125c"
    },
    "price": {
      "amount": "14.77",
      "currency": {
        "title": "USD",
        "value": "dd4a74f1-e6a3-4aa3-a902-1b54048fa760"
      }
    },
    "qty": {
      "amount": 281,
      "uom": {
        "title": "box",
        "value": "48f8c503-9f05-45a6-a168-c641d6dab4e4"
      }
    }
  },
  {
    "color": "Green",
    "mfg": {
      "title": "Goodyear Tire and Rubber Company",
      "value": "997c23b4-12f1-4ea2-99a6-82afa74e3fd2"
    },
    "part": {
      "title": "PTN-00938705",
      "value": "0b6f1367-4efa-40e5-ba67-ba7096a5e847"
    },
    "price": {
      "amount": "15.31",
      "currency": {
        "title": "USD",
        "value": "dd4a74f1-e6a3-4aa3-a902-1b54048fa760"
      }
    },
    "qty": {
      "amount": 203,
      "uom": {
        "title": "bag",
        "value": "c2cbc91a-f846-4e8d-9d2d-85d286da6000"
      }
    }
  },
  {
    "color": "Red",
    "mfg": {
      "title": "Bristol-Myers Squibb",
      "value": "de89672b-8125-44f7-8706-11b9e6677c51"
    },
    "part": {
      "title": "PTN-00204296",
      "value": "0a7efe93-72a5-455d-8bac-d33bd0651d9b"
    },
    "price": {
      "amount": "14.63",
      "currency": {
        "title": "USD",
        "value": "dd4a74f1-e6a3-4aa3-a902-1b54048fa760"
      }
    },
    "qty": {
      "amount": 196,
      "uom": {
        "title": "box",
        "value": "48f8c503-9f05-45a6-a168-c641d6dab4e4"
      }
    }
  },
  {
    "color": "Green",
    "mfg": {
      "title": "The Walt Disney Company",
      "value": "1d0fc791-64e6-454e-b08f-b914949bbe9d"
    },
    "part": {
      "title": "PTN-00976128",
      "value": "5af9ae88-670c-418c-84ca-0a1e4c606bbd"
    },
    "price": {
      "amount": "10.57",
      "currency": {
        "title": "USD",
        "value": "dd4a74f1-e6a3-4aa3-a902-1b54048fa760"
      }
    },
    "qty": {
      "amount": 124,
      "uom": {
        "title": "bag",
        "value": "c2cbc91a-f846-4e8d-9d2d-85d286da6000"
      }
    }
  }
]
